piedmont/__init__.py
piedmont/app.py
piedmont/base.py
piedmont/bridge.py
piedmont/config.py
piedmont/errors.py
piedmont/logger.py
piedmont/serials.py
piedmont/storage.py
piedmont/typing.py
piedmont-0.2.5.dist-info/licenses/LICENSE
piedmont-0.2.5.dist-info/METADATA
piedmont-0.2.5.dist-info/WHEEL
piedmont-0.2.5.dist-info/top_level.txt
piedmont-0.2.5.dist-info/RECORD
