Metadata-Version: 2.4
Name: piedmont
Version: 0.2.5
Summary: A python library that helps you to build ProtoPie Bridge App or plugin more efficiently
Home-page: https://github.com/nestorrid/piedmont
Author: Nestor
Author-email: admin@nestor.me
License-File: LICENSE
Requires-Dist: bidict==0.23.1; python_version >= "3.8"
Requires-Dist: certifi==2025.1.31; python_version >= "3.6"
Requires-Dist: charset-normalizer==3.4.1; python_version >= "3.7"
Requires-Dist: h11==0.14.0; python_version >= "3.7"
Requires-Dist: idna==3.10; python_version >= "3.6"
Requires-Dist: python-engineio==4.11.2; python_version >= "3.6"
Requires-Dist: python-socketio==5.12.1; python_version >= "3.8"
Requires-Dist: pyyaml==6.0.2; python_version >= "3.8"
Requires-Dist: requests==2.32.3; python_version >= "3.8"
Requires-Dist: simple-websocket==1.1.0; python_version >= "3.6"
Requires-Dist: urllib3==2.3.0; python_version >= "3.9"
Requires-Dist: websocket-client==1.8.0; python_version >= "3.8"
Requires-Dist: wsproto==1.2.0; python_full_version >= "3.7.0"
Dynamic: author
Dynamic: author-email
Dynamic: description
Dynamic: description-content-type
Dynamic: home-page
Dynamic: license-file
Dynamic: requires-dist
Dynamic: summary
